takumi_thrift/__init__.py
takumi_thrift/client.py
takumi_thrift/exc.py
takumi_thrift/processor.py
takumi_thrift/wrappers.py
takumi_thrift-0.2.2.dist-info/DESCRIPTION.rst
takumi_thrift-0.2.2.dist-info/METADATA
takumi_thrift-0.2.2.dist-info/metadata.json
takumi_thrift-0.2.2.dist-info/RECORD
takumi_thrift-0.2.2.dist-info/top_level.txt
takumi_thrift-0.2.2.dist-info/WHEEL
