Metadata-Version: 2.0
Name: takumi-thrift
Version: 0.2.2
Summary: Thriftpy instruments for passing metadata
Home-page: https://github.com/elemepi/takumi-thrift
Author: Eleme Lab
Author-email: imaralla@icloud.com
License: UNKNOWN
Platform: UNKNOWN
Requires-Dist: thriftpy
